{
	"info": {
		"_postman_id": "a46f2f6a-5e65-4074-bec0-6a0daee6c387",
		"name": "FresherManagement",
		"schema": "https://schema.getpostman.com/json/collection/v2.1.0/collection.json",
		"_exporter_id": "28959500"
	},
	"item": [
		{
			"name": "login",
			"request": {
				"method": "POST",
				"header": [],
				"body": {
					"mode": "raw",
					"raw": "{\r\n    \"username\": \"admin\",\r\n    \"password\": \"123\"\r\n}",
					"options": {
						"raw": {
							"language": "json"
						}
					}
				},
				"url": {
					"raw": "http://localhost:8080/login",
					"protocol": "http",
					"host": [
						"localhost"
					],
					"port": "8080",
					"path": [
						"login"
					]
				}
			},
			"response": []
		},
		{
			"name": "add fresher",
			"request": {
				"auth": {
					"type": "bearer",
					"bearer": [
						{
							"key": "token",
							"value": "eyJhbGciOiJIUzUxMiJ9.eyJzdWIiOiJhZG1pbiIsImV4cCI6MTcxOTk3NTE3MSwiaWF0IjoxNzE5OTc0ODExfQ.aJr7AYa8qmLphA0BjvBF4oUTr3AErrskra0HUOdCET-eDWtzeN8Y0dYoyij7hInflq81e4h0CDAzembA1OQOPQ",
							"type": "string"
						}
					]
				},
				"method": "POST",
				"header": [],
				"body": {
					"mode": "raw",
					"raw": "{\r\n  \"username\": \"frehs3\",\r\n  \"password\": \"password\",\r\n  \"name\": \"John Doe\",\r\n  \"dob\": \"1990-01-01\",\r\n  \"cccd\": \"123456789\",\r\n  \"sdt\": \"0901234567\",\r\n  \"address\": \"123 Main St\",\r\n  \"email\": \"johndoe@example.com\",\r\n  \"salary\": 5000,\r\n  \"state\": true,\r\n  \"language\": {\r\n    \"id\": 3\r\n  }\r\n}\r\n",
					"options": {
						"raw": {
							"language": "json"
						}
					}
				},
				"url": {
					"raw": "http://localhost:8080/fresher/add",
					"protocol": "http",
					"host": [
						"localhost"
					],
					"port": "8080",
					"path": [
						"fresher",
						"add"
					]
				}
			},
			"response": []
		},
		{
			"name": "add center",
			"request": {
				"auth": {
					"type": "bearer",
					"bearer": [
						{
							"key": "token",
							"value": "eyJhbGciOiJIUzUxMiJ9.eyJzdWIiOiJhZG1pbiIsImV4cCI6MTcxOTkwMjU1NCwiaWF0IjoxNzE5OTAyMTk0fQ.j5yLMuhbYPDs_eGLiRHDi-VoNgP3m_XTdCPYotcsdlaPxDlumX0QR70TXg9IPuYYQ5j5kMtE_hZJaP8NBDfp1g",
							"type": "string"
						}
					]
				},
				"method": "POST",
				"header": [],
				"body": {
					"mode": "raw",
					"raw": "{\r\n    \"name\": \"Center 6\",\r\n    \"sdt\": \"0328634\",\r\n    \"address\": \"NY\",\r\n    \"email\": \"c6@example.com\",\r\n    \"description\": \"This is a center 6\",\r\n    \"state\": true,\r\n    \"area\": {\r\n        \"id\": 2\r\n    },\r\n    \"manager\": {\r\n        \"id\": 9\r\n    }\r\n}\r\n",
					"options": {
						"raw": {
							"language": "json"
						}
					}
				},
				"url": {
					"raw": "http://localhost:8080/center/add",
					"protocol": "http",
					"host": [
						"localhost"
					],
					"port": "8080",
					"path": [
						"center",
						"add"
					]
				}
			},
			"response": []
		},
		{
			"name": "delete center",
			"request": {
				"auth": {
					"type": "bearer",
					"bearer": [
						{
							"key": "token",
							"value": "eyJhbGciOiJIUzUxMiJ9.eyJzdWIiOiJhZG1pbiIsImV4cCI6MTcxOTkwNjIxMSwiaWF0IjoxNzE5OTA1ODUxfQ.XIeBihv6VbVbvRS2OcnDy60DuYXINNO60qAcg1hs-7XLcXIbQ-wKLCURWGm22Ict6q-Rvs5i1GM5YCd2F6IHZw",
							"type": "string"
						}
					]
				},
				"method": "DELETE",
				"header": [],
				"url": {
					"raw": "http://localhost:8080/center/delete/7",
					"protocol": "http",
					"host": [
						"localhost"
					],
					"port": "8080",
					"path": [
						"center",
						"delete",
						"7"
					]
				}
			},
			"response": []
		},
		{
			"name": "update center",
			"request": {
				"auth": {
					"type": "bearer",
					"bearer": [
						{
							"key": "token",
							"value": "eyJhbGciOiJIUzUxMiJ9.eyJzdWIiOiJhZG1pbiIsImV4cCI6MTcxOTkwMzM0MSwiaWF0IjoxNzE5OTAyOTgxfQ.T1knVFg3Y0UgYRKJROpiB2EHjboRA6mYcsFyGuI1zMPGwxX1DbQAbRsQTzeoBMXgxmbTlrJFi693rTqiY7rqeQ",
							"type": "string"
						}
					]
				},
				"method": "PUT",
				"header": [],
				"body": {
					"mode": "raw",
					"raw": "{\r\n    \"name\": \"Center 5\",\r\n    \"sdt\": \"0328634\",\r\n    \"address\": \"NY\",\r\n    \"email\": \"c5@example.com\",\r\n    \"description\": \"This is a center 5\",\r\n    \"state\": true,\r\n    \"area\": {\r\n        \"id\": 2\r\n    },\r\n    \"manager\": {\r\n        \"id\": 9\r\n    }\r\n}\r\n",
					"options": {
						"raw": {
							"language": "json"
						}
					}
				},
				"url": {
					"raw": "http://localhost:8080/center/update/7",
					"protocol": "http",
					"host": [
						"localhost"
					],
					"port": "8080",
					"path": [
						"center",
						"update",
						"7"
					]
				}
			},
			"response": []
		},
		{
			"name": "list center",
			"request": {
				"auth": {
					"type": "bearer",
					"bearer": [
						{
							"key": "token",
							"value": "eyJhbGciOiJIUzUxMiJ9.eyJzdWIiOiJhZG1pbiIsImV4cCI6MTcxOTkwNzczNCwiaWF0IjoxNzE5OTA3Mzc0fQ.ZgLdIvY67dO2945D37zCTJWcXkdek1j1T6F0v9xfbMlc5Vysy_wKsyKgr7g-MPGlhac_hfU1AXubZaPoDMbnHA",
							"type": "string"
						}
					]
				},
				"method": "GET",
				"header": [],
				"url": {
					"raw": "http://localhost:8080/center/list",
					"protocol": "http",
					"host": [
						"localhost"
					],
					"port": "8080",
					"path": [
						"center",
						"list"
					]
				}
			},
			"response": []
		},
		{
			"name": "update fresher",
			"request": {
				"auth": {
					"type": "bearer",
					"bearer": [
						{
							"key": "token",
							"value": "eyJhbGciOiJIUzUxMiJ9.eyJzdWIiOiJhZG1pbiIsImV4cCI6MTcxOTk4ODgwMywiaWF0IjoxNzE5OTg4NDQzfQ.GWK55_NcCA7sdFhphgkwmJKRCBJwWNAS3UT1ItXUE2O6g14rKAMzZpANK-CcAHA7ffqYP6QQe-EkLzZUyT5e_Q",
							"type": "string"
						}
					]
				},
				"method": "PUT",
				"header": [],
				"body": {
					"mode": "raw",
					"raw": "{\r\n  \"username\": \"fresh3\",\r\n  \"password\": \"password\",\r\n  \"name\": \"John Doe\",\r\n  \"dob\": \"1990-01-01\",\r\n  \"cccd\": \"123456789\",\r\n  \"sdt\": \"0901234567\",\r\n  \"address\": \"123 Mai\",\r\n  \"email\": \"johndoe@example.com\",\r\n  \"salary\": 5000,\r\n  \"state\": true,\r\n  \"language\": {\r\n    \"id\": 3\r\n  }\r\n}\r\n",
					"options": {
						"raw": {
							"language": "json"
						}
					}
				},
				"url": {
					"raw": "http://localhost:8080/fresher/update/17",
					"protocol": "http",
					"host": [
						"localhost"
					],
					"port": "8080",
					"path": [
						"fresher",
						"update",
						"17"
					]
				}
			},
			"response": []
		},
		{
			"name": "delete fresher",
			"request": {
				"auth": {
					"type": "bearer",
					"bearer": [
						{
							"key": "token",
							"value": "eyJhbGciOiJIUzUxMiJ9.eyJzdWIiOiJhZG1pbiIsImV4cCI6MTcxOTk4ODgwMywiaWF0IjoxNzE5OTg4NDQzfQ.GWK55_NcCA7sdFhphgkwmJKRCBJwWNAS3UT1ItXUE2O6g14rKAMzZpANK-CcAHA7ffqYP6QQe-EkLzZUyT5e_Q",
							"type": "string"
						}
					]
				},
				"method": "DELETE",
				"header": [],
				"url": {
					"raw": "http://localhost:8080/fresher/delete/12",
					"protocol": "http",
					"host": [
						"localhost"
					],
					"port": "8080",
					"path": [
						"fresher",
						"delete",
						"12"
					]
				}
			},
			"response": []
		},
		{
			"name": "add fresher to center",
			"request": {
				"auth": {
					"type": "bearer",
					"bearer": [
						{
							"key": "token",
							"value": "eyJhbGciOiJIUzUxMiJ9.eyJzdWIiOiJhZG1pbiIsImV4cCI6MTcxOTk5NDE2MywiaWF0IjoxNzE5OTkzODAzfQ.MxLtuGexHJBxB8_U0Gw4I5hqLi2GAKnBnPtJ8af05GEkDQJ8RWgBMrVfX4tSTS_9Zv1uMFKhMKdg2x_YtYOaMA",
							"type": "string"
						}
					]
				},
				"method": "POST",
				"header": [],
				"body": {
					"mode": "raw",
					"raw": "{\r\n    \"fresher_id\": 17,\r\n    \"center_id\": 5\r\n}",
					"options": {
						"raw": {
							"language": "json"
						}
					}
				},
				"url": {
					"raw": "http://localhost:8080/center/add/fresher",
					"protocol": "http",
					"host": [
						"localhost"
					],
					"port": "8080",
					"path": [
						"center",
						"add",
						"fresher"
					]
				}
			},
			"response": []
		}
	]
}